Gangler/__init__.py
Gangler/pool.py
Gangler/prepare.py
Gangler-0.0.4.dist-info/LICENSE.txt
Gangler-0.0.4.dist-info/METADATA
Gangler-0.0.4.dist-info/WHEEL
Gangler-0.0.4.dist-info/top_level.txt
Gangler-0.0.4.dist-info/RECORD
