Metadata-Version: 2.1
Name: Gangler
Version: 0.0.4
Summary: A novel way to find target gene in suppressor or forward genetic screening
Home-page: UNKNOWN
Author: Guo_Zhengyang
Author-email: guozhengyang980525@yahoo.co.jp
License: MIT License
Platform: all
Classifier: Programming Language :: Python :: 3
Classifier: Development Status :: 4 - Beta
License-File: LICENSE.txt
Requires-Dist: pandas
Requires-Dist: matplotlib
Requires-Dist: seaborn
Requires-Dist: numpy
Requires-Dist: openpyxl
